jupyter_deploy_tf_aws_ec2_base/__init__.py
jupyter_deploy_tf_aws_ec2_base/template.py
jupyter_deploy_tf_aws_ec2_base/template/manifest.yaml
jupyter_deploy_tf_aws_ec2_base/template/variables.yaml
jupyter_deploy_tf_aws_ec2_base/template/engine/commands.tf
jupyter_deploy_tf_aws_ec2_base/template/engine/iam.tf
jupyter_deploy_tf_aws_ec2_base/template/engine/local-await-server.sh.tftpl
jupyter_deploy_tf_aws_ec2_base/template/engine/main.tf
jupyter_deploy_tf_aws_ec2_base/template/engine/outputs.tf
jupyter_deploy_tf_aws_ec2_base/template/engine/services.tf
jupyter_deploy_tf_aws_ec2_base/template/engine/variables.tf
jupyter_deploy_tf_aws_ec2_base/template/engine/waiter.tf
jupyter_deploy_tf_aws_ec2_base/template/engine/modules/ami_al2023/main.tf
jupyter_deploy_tf_aws_ec2_base/template/engine/modules/ami_al2023/outputs.tf
jupyter_deploy_tf_aws_ec2_base/template/engine/modules/ami_al2023/variables.tf
jupyter_deploy_tf_aws_ec2_base/template/engine/modules/certs_secret/main.tf
jupyter_deploy_tf_aws_ec2_base/template/engine/modules/certs_secret/outputs.tf
jupyter_deploy_tf_aws_ec2_base/template/engine/modules/certs_secret/variables.tf
jupyter_deploy_tf_aws_ec2_base/template/engine/modules/ec2_iam_role/main.tf
jupyter_deploy_tf_aws_ec2_base/template/engine/modules/ec2_iam_role/outputs.tf
jupyter_deploy_tf_aws_ec2_base/template/engine/modules/ec2_iam_role/variables.tf
jupyter_deploy_tf_aws_ec2_base/template/engine/modules/ec2_instance/main.tf
jupyter_deploy_tf_aws_ec2_base/template/engine/modules/ec2_instance/outputs.tf
jupyter_deploy_tf_aws_ec2_base/template/engine/modules/ec2_instance/variables.tf
jupyter_deploy_tf_aws_ec2_base/template/engine/modules/network/main.tf
jupyter_deploy_tf_aws_ec2_base/template/engine/modules/network/outputs.tf
jupyter_deploy_tf_aws_ec2_base/template/engine/modules/network/variables.tf
jupyter_deploy_tf_aws_ec2_base/template/engine/modules/s3_bucket/main.tf
jupyter_deploy_tf_aws_ec2_base/template/engine/modules/s3_bucket/outputs.tf
jupyter_deploy_tf_aws_ec2_base-0.3.0.dist-info/METADATA
jupyter_deploy_tf_aws_ec2_base-0.3.0.dist-info/WHEEL
jupyter_deploy_tf_aws_ec2_base-0.3.0.dist-info/entry_points.txt
jupyter_deploy_tf_aws_ec2_base-0.3.0.dist-info/licenses/LICENSE
jupyter_deploy_tf_aws_ec2_base-0.3.0.dist-info/RECORD
