Metadata-Version: 2.4
Name: jupyter-deploy-tf-aws-ec2-base
Version: 0.3.0
Summary: Base terraform template to deploy a JupyterLab application on an AWS EC2 instance.
Project-URL: Homepage, https://github.com/jupyter-infra/jupyter-deploy
Project-URL: github, https://github.com/jupyter-infra/jupyter-deploy/tree/main/libs/jupyter-deploy-tf-aws-ec2-base
Author-email: Jonathan Guinegagne <jggg@amazon.com>, Michael Chin <chnmch@amazon.com>, Brian Granger <brgrange@amazon.com>
License: MIT License
License-File: LICENSE
Requires-Python: >=3.12
Requires-Dist: boto3
Requires-Dist: boto3-stubs
Requires-Dist: mypy-boto3-ec2
Requires-Dist: mypy-boto3-ssm
